adbmanager/__init__.py
adbmanager/adbmanager.py
adbmanager/modules/__init__.py
adbmanager/modules/deviceInfo.py
adbmanager/modules/keyboard_events.json
adbmanager-0.0.3.dist-info/LICENSE
adbmanager-0.0.3.dist-info/METADATA
adbmanager-0.0.3.dist-info/WHEEL
adbmanager-0.0.3.dist-info/top_level.txt
adbmanager-0.0.3.dist-info/RECORD
